astrape
