Metadata-Version: 2.1
Name: astrape
Version: 0.7.4
Summary: Astrape: A STrategic, Reproducible & Accesible Project and Experiment.
Home-page: https://github.com/benchay1999/astrape
Download-URL: https://github.com/benchay1999/astrape/releases/tag/0.4.2.tar.gz
Author: Woosog Benjamin Chay
Author-email: benchay1@gmail.com
License: MIT
Project-URL: Bug Tracker, https://github.com/benchay1999/astrape/issues
Keywords: pypi,astrape,machine learning,pytorch lightning,lightning,pytorch-lightning
Classifier: Development Status :: 3 - Alpha
Classifier: Intended Audience :: Developers
Classifier: Topic :: Software Development :: Documentation
Classifier: License :: OSI Approved :: MIT License
Classifier: Programming Language :: Python :: 3
Classifier: Programming Language :: Python :: 3.7
Classifier: Programming Language :: Python :: 3.8
Classifier: Programming Language :: Python :: 3.9
License-File: LICENSE
